README.md
setup.py
miniretry/__init__.py
miniretry/main.py
miniretry/retry.py
miniretry.egg-info/PKG-INFO
miniretry.egg-info/SOURCES.txt
miniretry.egg-info/dependency_links.txt
miniretry.egg-info/entry_points.txt
miniretry.egg-info/top_level.txt