Metadata-Version: 1.0
Name: miniretry
Version: 0.1.5
Summary: Retry helpers
Home-page: http://github.com/miku/miniretry
Author: Martin Czygan
Author-email: martin.czygan@gmail.com
License: UNKNOWN
Platform: UNKNOWN
